git_interface/__init__.py
git_interface/archive.py
git_interface/branch.py
git_interface/cat_file.py
git_interface/constants.py
git_interface/datatypes.py
git_interface/exceptions.py
git_interface/helpers.py
git_interface/log.py
git_interface/ls.py
git_interface/pack.py
git_interface/rev_list.py
git_interface/shared.py
git_interface/show.py
git_interface/symbolic_ref.py
git_interface/tag.py
git_interface/utils.py
git_interface/smart_http/__init__.py
git_interface/smart_http/quart.py
git_interface/smart_http/ssh.py
git_interface-0.10.0.dist-info/METADATA
git_interface-0.10.0.dist-info/WHEEL
git_interface-0.10.0.dist-info/licenses/LICENSE
git_interface-0.10.0.dist-info/RECORD
