Metadata-Version: 2.3
Name: git-interface
Version: 0.10.0
Summary: Use the git cli from Python
Project-URL: Source Code, https://github.com/enchant97/python-git-interface
Project-URL: Change Log, https://github.com/enchant97/python-git-interface/blob/main/CHANGELOG.md
Project-URL: Documentation, https://python-git-interface.docs.enchantedcode.co.uk/
Author-email: Leo Spratt <contact@enchantedcode.co.uk>
License-Expression: MIT
License-File: LICENSE
Keywords: git,scm
Classifier: Framework :: AsyncIO
Classifier: Intended Audience :: Developers
Classifier: License :: OSI Approved :: MIT License
Classifier: Operating System :: OS Independent
Classifier: Programming Language :: Python :: 3
Classifier: Programming Language :: Python :: 3.9
Classifier: Programming Language :: Python :: 3.10
Classifier: Programming Language :: Python :: 3.11
Classifier: Programming Language :: Python :: 3.12
Classifier: Topic :: Software Development :: Libraries :: Python Modules
Classifier: Topic :: Software Development :: Version Control :: Git
Requires-Python: >=3.10
Requires-Dist: aiofiles>=23.2.1
Provides-Extra: quart
Requires-Dist: async-timeout>=4.0.2; extra == 'quart'
Requires-Dist: quart>=0.16.3; extra == 'quart'
Provides-Extra: ssh
Requires-Dist: asyncssh>=2.9.0; extra == 'ssh'
